easy_serve/__init__.py
easy_serve/server.py
easy_serve-0.0.1.dist-info/LICENSE
easy_serve-0.0.1.dist-info/METADATA
easy_serve-0.0.1.dist-info/WHEEL
easy_serve-0.0.1.dist-info/top_level.txt
easy_serve-0.0.1.dist-info/RECORD
