Metadata-Version: 2.2
Name: easy_serve
Version: 0.0.1
Summary: High level abstraction for deploying simple machine learning models using Flask
Author-email: Tan Chia Yan <tchiayan@gmail.com>
License: MIT License
Project-URL: Homepage, https://github.com/tchiayan/easy_serve
Project-URL: Bug Tracker, https://github.com/tchiayan/easy_serve/issues
Classifier: Programming Language :: Python :: 3
Classifier: License :: OSI Approved :: MIT License
Classifier: Operating System :: OS Independent
Requires-Python: >=3.9
License-File: LICENSE
Requires-Dist: flask
Requires-Dist: flask_cors
Requires-Dist: requests
